fast_gem/__init__.py
fast_gem/gem.py
fast_gem/functional/__init__.py
fast_gem/functional/gem.py
fast_gem/functional/gem1d.py
fast_gem/functional/gem2d.py
fast_gem/functional/gem3d.py
fast_gem/functional/gem_torch.py
fast_gem/functional/gem_triton.py
fast_gem/functional/triton_utils.py
fast_gem-0.0.5.dist-info/LICENSE
fast_gem-0.0.5.dist-info/METADATA
fast_gem-0.0.5.dist-info/WHEEL
fast_gem-0.0.5.dist-info/top_level.txt
fast_gem-0.0.5.dist-info/RECORD
