Metadata-Version: 2.1
Name: fast_gem
Version: 0.0.5
Summary: Efficient and general implementation of Generalized Mean Pooling (GeM)
Home-page: https://github.com/Kitsunetic/fast-GeM
Author: Kitsunetic
Author-email: jh.shim.gg@gmail.com
License-File: LICENSE
